{
  "total":800,
  "rows":[
    {
      "a": "20365987",
      "b": "老王",
      "d": "经理",
      "e": "13004653721",
      "f": "02578",
      "g": "商务一部",
      "h": "2017-04-26"
    },
    {
      "a": "20365987",
      "b": "老王",
      "d": "经理",
      "e": "13004653721",
      "f": "02578",
      "g": "商务一部",
      "h": "2017-04-26"
    },
    {
      "a": "20365987",
      "b": "老王",
      "d": "经理",
      "e": "13004653721",
      "f": "02578",
      "g": "商务一部",
      "h": "2017-04-26"
    }
  ]
}