{
  "total":800,
  "rows":[
    {
      "a": "20365987",
      "b": "浙江惠点",
      "c": "厂内食堂",
      "d": "拱墅一代",
      "e": "隔壁老王",
      "f": "浙江 杭州 拱墅",
      "g": "2017-04-26",
      "h": "1",
      "i": "13004653721"
    },
    {
      "a": "20365987",
      "b": "浙江惠点",
      "c": "厂内食堂",
      "d": "拱墅一代",
      "e": "隔壁老王",
      "f": "浙江 杭州 拱墅",
      "g": "2017-04-26",
      "h": "1",
      "i": "13004653721"
    },
    {
      "a": "20365987",
      "b": "浙江惠点",
      "c": "厂内食堂",
      "d": "拱墅一代",
      "e": "隔壁老王",
      "f": "浙江 杭州 拱墅",
      "g": "2017-04-26",
      "h": "1",
      "i": "13004653721"
    }
  ]
}